{
  "title": "AE/PR脚本模板-300个酷炫创意文字标题动态排版预设 Kinetic Typography Pack V6",
  "slug": "ae-prjiao-ben-mo-ban-300ge-ku-xuan-chuang-yi-wen-zi-biao-ti-dong-tai-pai-ban-yu-she-kinetic-typography-pack-v6",
  "author": "大众脸",
  "post_date": "2021/11/05 00:04",
  "source_url": "https://www.lookae.com/kinetic-v6/",
  "category": "aescripts",
  "tags": [
    "AE模板",
    "AE脚本",
    "PR脚本"
  ],
  "content": "Kinetic Typography Pack V6 提供超过300个酷炫创意文字标题动态排版预设，支持 After Effects 和 Premiere Pro。所有预设均可自定义字体、颜色、内容，并支持循环动画（6秒）。适用于多种分辨率（4K、高清、移动、方形），无需额外插件，兼容性强，支持多语言文本及通用控制器，包含视频教程与 PremiumBuilder 扩展工具。",
  "image_urls": [
    "https://www.lookae.com/wp-content/uploads/2021/11/Kinetic-Typography-Pack-28757522.jpg"
  ],
  "video_urls": [
    "https://cloud.video.taobao.com//play/u/705956171/p/1/e/6/t/1/335587891490.mp4"
  ],
  "supported_versions": "CC 2020 – CC 2019",
  "supported_os": "",
  "download_links": [
    {
      "name": "城通网盘",
      "url": "https://url62.ctfile.com/f/680462-519662846-318931"
    },
    {
      "name": "百度网盘",
      "url": "https://pan.baidu.com/s/1dQQDqU7zdFmdhyeSkB3aUQ"
    },
    {
      "name": "阿里云盘",
      "url": "https://www.aliyundrive.com/s/7S8whTXJNJw"
    }
  ],
  "other": {
    "related_links": [
      "https://www.lookae.com/after-effects/other-after-effects/",
      "https://item.taobao.com/item.htm?spm=a1z10.1.w4004-2793089344.4.MUvxbV&id=37289930486"
    ],
    "features": [
      "300个动力学排版预设",
      "包含AE模板、AE脚本、Premiere Pro脚本、PR预设",
      "包含PremiumBuilder扩展工具",
      "可调整大小的合成（4K、高清、移动、方形）",
      "100% AE制作",
      "循环动画（6秒）",
      "多语言文本支持",
      "适用于任何字体",
      "无需插件",
      "轻松文本定制",
      "色彩控制",
      "包含Universaliser控制器（兼容任何语言）",
      "包含视频教程",
      "PremiumBuilder功能：主页按钮、动画可视化、最小化/最大化、加入收藏夹、侧边菜单开关、全局或分类搜索"
    ]
  }
}