{
  "title": "AE/PR插件-抽象梦幻星云背景生成器 Mettle Flux v1.16.3 Win",
  "slug": "ae-prcha-jian-chou-xiang-meng-huan-xing-yun-bei-jing-sheng-cheng-qi-mettle-flux-v1-16-3-win",
  "author": "大众脸",
  "post_date": "2025/04/02 12:12",
  "source_url": "https://www.lookae.com/flux-1163/",
  "category": "aechajian",
  "tags": [
    "AE插件",
    "PR插件"
  ],
  "content": "Mettle Flux 是一款用于制作漂亮抽象梦幻背景动画的插件，可生成银河、星云、分形噪波等效果。支持 GPU 加速和体积渲染功能，兼容软件内置摄像机，便于动画制作，并内置预设预览器，可直接预览和使用预设效果。",
  "image_urls": [
    "https://www.lookae.com/wp-content/uploads/2019/09/Mettle-Flux.jpg"
  ],
  "video_urls": [],
  "supported_versions": "After Effects: 2025, 2024, 2023, 2022, 2021, 2020, CC 2019, CC 2018, CC 2017, CC 2015; Premiere: 2025, 2023, 2022, 2021, 2020, CC 2019, CC 2018, CC 2017, CC 2015",
  "supported_os": "Windows",
  "download_links": [
    {
      "name": "城通网盘 - 插件",
      "url": "https://url70.ctfile.com/f/2827370-1488809912-e75c19?p=4431"
    },
    {
      "name": "百度网盘 - 插件",
      "url": "https://pan.baidu.com/s/1AhSa1gZFQrdH_6380aU9Mw?pwd=jtpt"
    },
    {
      "name": "阿里云盘 - 插件",
      "url": "https://www.alipan.com/s/tRHkU7CTU9U"
    },
    {
      "name": "城通网盘 - 教程",
      "url": "https://lookae.ctfile.com/fs/680462-396949334"
    },
    {
      "name": "百度网盘 - 教程",
      "url": "https://pan.baidu.com/s/1melARqCCB2zFsFoFqII2nw"
    }
  ],
  "other": {
    "update_notes": "1.16.3更新内容：增加了2025的兼容性"
  }
}