{
  "title": "AE插件-目标对象自动跟踪视觉特效生成器 Tracery 1.1 Win",
  "slug": "aecha-jian-mu-biao-dui-xiang-zi-dong-gen-zong-shi-jue-te-xiao-sheng-cheng-qi-tracery-1-1-win",
  "author": "大众脸",
  "post_date": "2025/06/04 09:51",
  "source_url": "https://www.lookae.com/tracery-11/",
  "category": "aechajian",
  "tags": [
    "AE插件"
  ],
  "content": "Tracery 是一款功能强大的 After Effects 插件，旨在通过色键自动跟踪对象或区域，并生成高度可自定义的图形叠加层。您可以直接从素材中创建复杂的视觉杂乱效果、数据驱动的示意图、跟踪器可视化以及风格化的动态图形元素。\n\n插件主要特点包括：自动颜色区域跟踪、动态可视化系统、多目标支持（最多512个对象）、性能优化（多线程与可调质量设置）以及与 After Effects 的无缝集成，无需外部应用程序或数据。",
  "image_urls": [
    "https://www.lookae.com/wp-content/uploads/2025/05/Tracery-.jpg"
  ],
  "video_urls": [
    "http://cloud.video.taobao.com/play/u/null/p/1/e/6/t/1/518693951075.mp4"
  ],
  "supported_versions": "AE 2025, 2024, 2023, 2022, 2021, 2020, CC 2019, CC 2018, CC 2017, CC 2015, CC 2014",
  "supported_os": "Win",
  "download_links": [
    {
      "name": "城通网盘",
      "url": "https://url70.ctfile.com/f/2827370-1511715091-92f7e8?p=4431"
    },
    {
      "name": "百度网盘",
      "url": "https://pan.baidu.com/s/1Ot2vYN8huUws42E4JVJvIw?pwd=3xh2"
    },
    {
      "name": "阿里云盘",
      "url": "https://www.alipan.com/s/o7RD2m93h75"
    }
  ],
  "other": {
    "password": {
      "城通网盘": "6688",
      "百度网盘": "3xh2"
    },
    "update_notes": {
      "version": "1.1",
      "new_features": [
        "添加了3种新的线路连接类型：星型、完整型、MST（最小生成树）"
      ],
      "fixes": [
        "解决了由过时的 MSVCP140.dll 库导致的严重 AE 崩溃",
        "修复了当合成中存在第三方 OpenGL 插件时出现的插件兼容性问题",
        "Tracery 日志文件不再写入桌面"
      ]
    }
  }
}