{
  "title": "AE插件-自定义遮罩图层变形扭曲 BAO Layer Sculptor 1.1.4 Win/Mac版+使用教程",
  "slug": "aecha-jian-zi-ding-yi-zhe-zhao-tu-ceng-bian-xing-niu-qu-bao-layer-sculptor-1-1-4-win-macban-shi-yong-jiao-cheng",
  "author": "大众脸",
  "post_date": "2019/04/23 22:24",
  "source_url": "https://www.lookae.com/bao-layer-sculptor-114/",
  "category": "aechajian",
  "tags": [
    "AE插件",
    "Win/Mac"
  ],
  "content": "插件 BAO Layer Sculptor 可以将自定义遮罩画面进行精准的变形扭曲。Precise layer warping and sculpting plugin for After Effects. Draw a mask exactly where you need it and warp it with perfect precision。",
  "image_urls": [
    "https://www.lookae.com/wp-content/uploads/2018/11/BAO-Layer-Sculptor.jpg"
  ],
  "video_urls": [],
  "supported_versions": "After Effects CS6 – CC 2019",
  "supported_os": "Win/Mac",
  "download_links": [
    {
      "name": "城通网盘下载",
      "url": "https://lookae.ctfile.com/fs/680462-367832861"
    },
    {
      "name": "百度网盘下载",
      "url": "https://pan.baidu.com/s/1DnW5WRjlwFgdzk6SS_blQw"
    }
  ],
  "other": {
    "tutorial_info": {
      "baidu_pan_code": "1bhp"
    },
    "plugin_website": "https://aescripts.com/bao-layer-sculptor/",
    "changelog": "修复了OpenGL纹理大小问题。"
  }
}