{
  "title": "AE教程-MG脚本工具 Motion Tools 使用教程（中文字幕）+AE脚本下载",
  "slug": "aejiao-cheng-mgjiao-ben-gong-ju-motion-tools-shi-yong-jiao-cheng-zhong-wen-zi-mu-aejiao-ben-xia-zai",
  "author": "大众脸",
  "post_date": "2019-08-21",
  "source_url": "https://www.lookae.com/motion-tools/",
  "category": "aescripts",
  "tags": [
    "AE教程",
    "AE脚本",
    "MG与动画",
    "中文字幕"
  ],
  "content": "Motion Tools 是由 Motion Design School 出品的 AE 脚本，专为简化 MG 动画流程而设计。它整合了轴中心点调整、关键帧调整、弹性、克隆、添加空物体层等常用功能，避免安装大量单一功能脚本带来的冗余。",
  "image_urls": [
    "https://www.lookae.com/wp-content/uploads/2019/08/Motion-Tools.jpg"
  ],
  "video_urls": [],
  "supported_versions": "",
  "supported_os": "",
  "download_links": [
    {
      "name": "城通网盘下载",
      "url": "https://lookae.ctfile.com/fs/680462-393737267"
    },
    {
      "name": "百度网盘下载",
      "url": "https://pan.baidu.com/s/1uDyK88xqotjWi7NhhZzm-A"
    }
  ],
  "other": {
    "translator": "公众号《MG与动画》",
    "original_author": "Motion Design School"
  }
}