{
  "title": "AE脚本：水墨油彩掉落晕开显示动画生成器 Watercolor Motion Kit + 使用教程",
  "slug": "aejiao-ben-shui-mo-you-cai-diao-luo-yun-kai-xian-shi-dong-hua-sheng-cheng-qi-watercolor-motion-kit-shi-yong-jiao-cheng",
  "author": "大众脸",
  "post_date": "2016-11-21T23:29:00Z",
  "source_url": "https://www.lookae.com/watercolor-2/",
  "category": "aescripts",
  "tags": [
    "AE预设"
  ],
  "content": "Watercolor Motion Kit 是一款专为 Adobe After Effects 设计的脚本工具，可快速生成水墨油彩风格的掉落、晕染、扩散类动态效果。适用于片头动画、文字展示、品牌视觉等场景。支持从 AE CS5 到 CC 2016 及更高版本，无需额外插件，文件大小约 800MB，格式为 .jsxbin。提供配套使用教程，帮助用户快速掌握操作方法。",
  "image_urls": [
    "https://www.lookae.com/wp-content/uploads/2016/11/wmk-hero2.jpg"
  ],
  "video_urls": [
    "https://0.s3.envato.com/h264-video-previews/8b93b775-770f-4bf5-affd-30d09b34e07b/17286607.mp4?_=1"
  ],
  "supported_versions": "AE CS5 - CC 2016 及更高版本",
  "supported_os": "",
  "download_links": [
    {
      "name": "AE脚本：水墨油彩掉落晕开显示动画生成器 Watercolor Motion Kit + 使用教程",
      "url": "http://lookae.ctfile.com/fs/15D161597700"
    }
  ],
  "other": {
    "resolution": "无限制",
    "plugins_required": "无需外置插件",
    "file_size": "800M",
    "file_format": ".jsxbin",
    "tutorial": "修改视频教程",
    "music": "无音乐",
    "duration": "none",
    "item_id": "17286607",
    "related_links": [
      "https://www.lookae.com/after-effects/other-after-effects/",
      "https://item.taobao.com/item.htm?spm=a1z10.1.w4004-2793089344.4.MUvxbV&id=37289930486",
      "https://www.lookae.com/sponsor/"
    ]
  }
}