{
  "title": "AE脚本：世界地图任意位置路径展示动画Aescripts GEOlayers 2 V1.2.1+使用教程",
  "slug": "aejiao-ben-shi-jie-di-tu-ren-yi-wei-zhi-lu-jing-zhan-shi-dong-hua-aescripts-geolayers-2-v1-2-1-shi-yong-jiao-cheng",
  "author": "大众脸",
  "post_date": "2017/11/17 13:00",
  "source_url": "https://www.lookae.com/geolayers2121/",
  "category": "aescripts",
  "tags": [
    "Aescaripts",
    "AE脚本"
  ],
  "content": "通过脚本可以简单快速的链接世界上任意位置方位，包括国家，街道，建筑等地图。拥有高清卫星地图，地图的飞入飞出动画等，对于制作地图定位，路线路径展示非常不错，还包含14种地图样式。可以配合 Trapcode Mir 插件模拟制作一些三维立体效果。GEOlayers 2 连接 After Effects 到图像瓦片服务器以获取最新地图，并提供对世界各种地理空间特征的直接访问。可以轻松将建筑物绘制到 After Effects 形状图层，突出显示特定国家边界、街道、湖泊、河流、地点，标记区域，动画路线，挤压建筑物等。",
  "image_urls": [
    "https://www.lookae.com/wp-content/uploads/2016/12/GEOlayers-2.jpg"
  ],
  "video_urls": [],
  "supported_versions": "AE CC 2015 – CC2018",
  "supported_os": "Win/Mac",
  "download_links": [
    {
      "name": "城通网盘下载",
      "url": "https://lookae.ctfile.com/fs/680462-228578490"
    },
    {
      "name": "百度云网盘下载",
      "url": "https://pan.baidu.com/s/1nv65hBN"
    },
    {
      "name": "使用视频教程",
      "url": "http://lookae.ctfile.com/fs/OKc162908492"
    }
  ],
  "other": {
    "official_website": "http://aescripts.com/geolayers/",
    "taobao_store": "https://lookae.taobao.com/"
  }
}