{
  "title": "AE脚本-1122个超级无敌文字标题排版动画大合集预设 TypoKing V7.0",
  "slug": "aejiao-ben-1122ge-chao-ji-wu-di-wen-zi-biao-ti-pai-ban-dong-hua-da-he-ji-yu-she-typoking-v7-0",
  "author": "大众脸",
  "post_date": "2021/12/15 14:23",
  "source_url": "https://www.lookae.com/typoking-1122/",
  "category": "aescripts",
  "tags": [
    "AE脚本",
    "文字标题"
  ],
  "content": "精美时尚现代简洁复古婚礼运动排版边框文字等27类超过1122个新颖个性文字标题排版动画。使用自带的TypoKing脚本扩展预览，需要什么点击即可，能够修改文字内容和颜色等属性，非常方便。",
  "image_urls": [
    "https://www.lookae.com/wp-content/uploads/2021/12/TypoKing-V7-11263341.jpg"
  ],
  "video_urls": [
    "https://cloud.video.taobao.com//play/u/705956171/p/1/e/6/t/1/340358204573.mp4"
  ],
  "supported_versions": "AE CC 2020 或更高",
  "supported_os": "Win 和 Mac",
  "download_links": [
    {
      "name": "城通网盘",
      "url": "https://url62.ctfile.com/f/680462-529021072-2cd799"
    },
    {
      "name": "百度网盘",
      "url": "https://pan.baidu.com/s/1ykEaEVkP5VfE_Zd_61RRXg"
    },
    {
      "name": "阿里云盘",
      "url": "https://www.aliyundrive.com/s/QuS9MunsSpL"
    }
  ],
  "other": {
    "resolution": "不限制",
    "file_size": "382M",
    "extension_included": "自带TypoKing脚本",
    "music": "无音乐",
    "help": "安装方法+视频教程",
    "password": "城通网盘访问密码：6688，百度网盘提取码：pxc5",
    "related_link": "https://www.lookae.com/typoking-v7/"
  }
}