{
  "title": "AE脚本-6000种社交媒体文字标题排版设计转场LOGO图标MG图形动画 V6.0",
  "slug": "aejiao-ben-6000chong-she-jiao-mei-ti-wen-zi-biao-ti-pai-ban-she-ji-zhuan-chang-logotu-biao-mgtu-xing-dong-hua-v6-0",
  "author": "大众脸",
  "post_date": "2021-11-02",
  "source_url": "https://www.lookae.com/graphics-v6/",
  "category": "aescripts",
  "tags": [
    "AE脚本",
    "AtomX"
  ],
  "content": "Trendy Graphics V6 是一套通过 AtomX 脚本在 After Effects 中调用的超大型动态图形预设包，含 6000+ 社交竖屏、标题排版、LOGO 演绎、转场、图标、背景、粒子、音效等模块，可视化预览即可直接应用于时间线，帮助 Vlogger 与专业剪辑师快速完成高质视频包装。V6 新增 80+ 竖屏排版并修复已知问题，建议重新安装以获得最佳体验。",
  "image_urls": [
    "https://www.lookae.com/wp-content/uploads/2021/11/All-In-One-Pack-V6-24321544.jpg"
  ],
  "video_urls": [
    "https://cloud.video.taobao.com//play/u/705956171/p/1/e/6/t/1/326591101723.mp4"
  ],
  "supported_versions": "AE CC 2019 及以上",
  "supported_os": "Win & Mac",
  "download_links": [
    {
      "name": "城通网盘",
      "url": "https://url62.ctfile.com/f/680462-519408397-d2ebc2"
    },
    {
      "name": "百度网盘",
      "url": "https://pan.baidu.com/s/1ORBeYW7tXe1e06EYFcxi7g"
    },
    {
      "name": "阿里云盘",
      "url": "https://www.aliyundrive.com/s/ouYsVukMify"
    }
  ],
  "other": {
    "file_size": "2.71 GB",
    "included_script": "AtomX 3.0.5（已集成）",
    "audio": "无背景音乐，含转场音效",
    "resolution": "不限制",
    "installation_note": "安装后请勿移动安装文件，否则失效",
    "passwords": {
      "城通网盘": "6688",
      "百度网盘": "v1zf"
    },
    "related_links": {
      "更多AtomX脚本预设": "https://www.lookae.com/tag/atomx/",
      "PR版同款预设": "https://www.lookae.com/trendy-graphics-56/"
    }
  }
}