{
  "title": "Win/Mac版：红巨人调色插件套装 Red Giant Magic Bullet Suite v12.1.4",
  "slug": "win-macban-hong-ju-ren-diao-se-cha-jian-tao-zhuang-red-giant-magic-bullet-suite-v12-1-4",
  "author": "大众脸",
  "post_date": "2016/02/23 11:46",
  "source_url": "https://www.lookae.com/mb1214/",
  "category": "aechajian",
  "tags": [
    "AE插件",
    "FCPX",
    "FCPX插件",
    "MAC",
    "PR插件",
    "Win/Mac"
  ],
  "content": "Red Giant 红巨人调色插件套装 Magic Bullet Suite v12.1.4 进行了重大更新，不仅加入了新插件，还对多个现有插件进行了功能增强和界面优化。该套装包含多个专业调色与图像处理工具，适用于影视后期制作，支持多种主流剪辑与合成软件，帮助用户快速实现电影级调色效果。",
  "image_urls": [
    "https://www.lookae.com/wp-content/uploads/2015/02/MBS12.jpg"
  ],
  "video_urls": [],
  "supported_versions": "Davinci Resolve 11, 12; Adobe Premiere Pro C6 – CC 2015; Adobe Photoshop C5 – CC 2015; Adobe After Effects C6 – CC 2015; Avid Media Composer; Vegas Pro; Motion 4, 5; Final Cut Pro X, 7",
  "supported_os": "Mac/Win",
  "download_links": [
    {
      "name": "Win 系统一键安装版 RedGiant Magic Bullet Suite v12.1.4.CE",
      "url": "http://lookae.ctfile.com/file/143442548"
    },
    {
      "name": "Windows 版本下载",
      "url": "https://pan.baidu.com/s/1dEbqnct"
    },
    {
      "name": "Mac OSX 版本下载",
      "url": "https://pan.baidu.com/s/1jGXIgv0"
    }
  ],
  "other": {
    "serial_keys": {
      "Magic Bullet Colorista III": "CL3K1245864582715611",
      "Magic Bullet Cosmo 2.0": "MBOK1245884249899024",
      "Magic Bullet Film 1.0": "FILK1245884461501298",
      "Magic Bullet Looks 3.0": "MBLK1245875960562349",
      "Magic Bullet Mojo 2.0": "MBMK1245868236810616",
      "Red Giant Denoiser II": "MBNK1245865095746168",
      "Red Giant LUT Buddy": "免费"
    },
    "plugin_list": [
      "Magic Bullet Colorista III 1.1.4",
      "Magic Bullet Cosmo 2.0.4",
      "Magic Bullet Film 1.0.6",
      "Magic Bullet Looks 3.1.4",
      "Magic Bullet Mojo 2.0.5",
      "Red Giant Denoiser II 1.4.6",
      "Red Giant LUT Buddy 1.0.3"
    ],
    "update_notes": [
      "New Looks TrackPad mode hotkeys",
      "Fixes a potential issue with the Colorista III Keyer"
    ]
  }
}